setup.py
cryptic/__init__.py
cryptic/cryptic.py
cryptic.egg-info/PKG-INFO
cryptic.egg-info/SOURCES.txt
cryptic.egg-info/dependency_links.txt
cryptic.egg-info/entry_points.txt
cryptic.egg-info/requires.txt
cryptic.egg-info/top_level.txt