Metadata-Version: 1.0
Name: cryptic
Version: 0.0.1
Summary: Encrypted messaging using GnuPG
Home-page: http://github.com/samliu/cryptic
Author: Sam Liu
Author-email: sam@ambushnetworks.com
License: MIT
Platform: UNKNOWN
Classifier: Development Status :: 4 - Beta
Classifier: Intended Audience :: End Users/Desktop
Classifier: Operating System :: OS Independent
